pytrackr
