Metadata-Version: 1.0
Name: pytrackr
Version: 0.0.4
Summary: Interface to the TrackR API
Home-page: http://github.com/w1ll1am23/pytrackr
Author: William Scanlon
Author-email: UNKNOWN
License: MIT
Platform: UNKNOWN
